[
	{
		"__TYPE__": "SharedSliceContent",
		"variation": "default",
		"primary": {
			"heading": {
				"__TYPE__": "StructuredTextContent",
				"value": [
					{
						"type": "heading1",
						"content": {
							"text": "Feature"
						}
					}
				]
			},
			"subheading": {
				"__TYPE__": "StructuredTextContent",
				"value": [
					{
						"type": "paragraph",
						"content": {
							"text": "Commodo ullamco id fugiat duis fugiat aute Lorem ipsum cupidatat pariatur ullamco sunt et."
						}
					}
				]
			},
			"body": {
				"__TYPE__": "StructuredTextContent",
				"value": [
					{
						"type": "paragraph",
						"content": {
							"text": "Magna aliqua nisi aute voluptate cillum labore id amet occaecat pariatur id elit."
						}
					}
				]
			},
			"button_text": {
				"__TYPE__": "FieldContent",
				"value": "hold",
				"type": "Text"
			},
			"button_link": {
				"__TYPE__": "LinkContent",
				"value": {
					"__TYPE__": "ExternalLink",
					"url": "http://google.com"
				}
			},
			"cans_image": {
				"origin": {
					"id": "main",
					"url": "https://images.unsplash.com/photo-1600804931749-2da4ce26c869",
					"width": 3199,
					"height": 3199
				},
				"url": "https://images.unsplash.com/photo-1600804931749-2da4ce26c869",
				"width": 3199,
				"height": 3199,
				"edit": {
					"zoom": 1,
					"crop": {
						"x": 0,
						"y": 0
					},
					"background": "transparent"
				},
				"credits": null,
				"alt": null,
				"__TYPE__": "ImageContent",
				"thumbnails": {}
			},
			"second_heading": {
				"__TYPE__": "StructuredTextContent",
				"value": [
					{
						"type": "heading2",
						"content": {
							"text": "Beside"
						}
					}
				]
			},
			"second_body": {
				"__TYPE__": "StructuredTextContent",
				"value": [
					{
						"type": "paragraph",
						"content": {
							"text": "Consectetur exercitation deserunt dolore pariatur cillum quis. Excepteur aliqua nostrud sit incididunt exercitation nostrud ullamco est non aute do aliquip occaecat sit. Labore deserunt consectetur nulla in."
						}
					}
				]
			}
		},
		"items": []
	}
]